galeodes/__init__.py
galeodes/__main__.py
galeodes/galeodes.py
galeodes-0.7.dist-info/LICENSE
galeodes-0.7.dist-info/METADATA
galeodes-0.7.dist-info/WHEEL
galeodes-0.7.dist-info/entry_points.txt
galeodes-0.7.dist-info/top_level.txt
galeodes-0.7.dist-info/RECORD
