Metadata-Version: 2.1
Name: galeodes
Version: 0.7
Summary: Browsers options
Home-page: https://github.com/qeeqbox/galeodes
Author: QeeqBox
Author-email: gigaqeeq@gmail.com
License: AGPL-3.0
Platform: UNKNOWN
Requires-Python: >=3.5
Requires-Dist: Pillow
Requires-Dist: requests
Requires-Dist: selenium
